indifference/__init__.py
indifference/core.py
indifference/py.typed
indifference-0.1.0.dist-info/WHEEL
indifference-0.1.0.dist-info/METADATA
indifference-0.1.0.dist-info/RECORD
