Metadata-Version: 2.3
Name: indifference
Version: 0.1.0
Summary: Track and compare differences between Python objects.
Author: Arseny Boykov (Bobronium)
Author-email: Arseny Boykov (Bobronium) <hi@bobronium.me>
License: MIT
Classifier: Programming Language :: Python :: 3
Classifier: Programming Language :: Python :: 3 :: Only
Classifier: Programming Language :: Python :: 3.10
Classifier: Programming Language :: Python :: 3.11
Classifier: Programming Language :: Python :: 3.12
Classifier: Programming Language :: Python :: 3.13
Classifier: Programming Language :: Python :: 3.14
Classifier: License :: OSI Approved :: MIT License
Classifier: Development Status :: 3 - Alpha
Classifier: Intended Audience :: Developers
Classifier: Topic :: Software Development :: Libraries
Requires-Dist: pytest-assert-type>=0.1.3
Requires-Dist: indifference[lint] ; extra == 'dev'
Requires-Dist: indifference[typecheck] ; extra == 'dev'
Requires-Dist: indifference[test] ; extra == 'dev'
Requires-Dist: indifference[docs] ; extra == 'dev'
Requires-Dist: mkdocs-material ; extra == 'docs'
Requires-Dist: mkdocstrings[python] ; extra == 'docs'
Requires-Dist: mkdocs-autorefs ; extra == 'docs'
Requires-Dist: mkdocs-section-index ; extra == 'docs'
Requires-Dist: pdoc3>=0.11.6 ; extra == 'docs'
Requires-Dist: lazydocs>=0.4.8 ; extra == 'docs'
Requires-Dist: ruff>=0.5 ; extra == 'lint'
Requires-Dist: pytest>=8 ; extra == 'test'
Requires-Dist: pytest-cov>=5 ; extra == 'test'
Requires-Dist: coverage>=7.4 ; extra == 'test'
Requires-Dist: pytest-assert-type>=0.1.2 ; extra == 'test'
Requires-Dist: typing-extensions ; python_full_version < '3.12' and extra == 'test'
Requires-Dist: mypy>=1.10 ; extra == 'typecheck'
Requires-Dist: pyright>=1.1.400 ; extra == 'typecheck'
Requires-Python: >=3.10
Project-URL: Homepage, https://github.com/Bobronium/indifference
Project-URL: Issues, https://github.com/Bobronium/indifference/issues
Project-URL: Source, https://github.com/Bobronium/indifference
Provides-Extra: dev
Provides-Extra: docs
Provides-Extra: lint
Provides-Extra: test
Provides-Extra: typecheck
